zyb_ai/__init__.py
zyb_ai/api.py
zyb_ai/front.py
zyb_ai/tools.py
zyb_ai-0.1.2.dist-info/LICENSE
zyb_ai-0.1.2.dist-info/METADATA
zyb_ai-0.1.2.dist-info/WHEEL
zyb_ai-0.1.2.dist-info/top_level.txt
zyb_ai-0.1.2.dist-info/RECORD
